flask_fido_u2f
