Metadata-Version: 1.1
Name: Flask-FIDO-U2F
Version: 0.4.4
Summary: A Flask plugin that adds FIDO U2F support.
Home-page: https://github.com/herrjemand/flask-fido-u2f
Author: Ackermann Yuriy
Author-email: ackermann.yuriy@gmail.com
License: MIT
Keywords: flask fido u2f 2fa
Platform: any
Classifier: Environment :: Web Environment
Classifier: License :: OSI Approved :: MIT License
Classifier: Operating System :: OS Independent
Classifier: Development Status :: 5 - Production/Stable
Classifier: Intended Audience :: Developers
Classifier: Intended Audience :: System Administrators
Classifier: Programming Language :: Python :: 3
Classifier: Programming Language :: Python :: 3.3
Classifier: Programming Language :: Python :: 3.4
Classifier: Programming Language :: Python :: 3.5
Classifier: Programming Language :: Python :: Implementation :: PyPy
Classifier: Topic :: Internet
Classifier: Topic :: Security :: Cryptography
Classifier: Topic :: Software Development :: Libraries :: Python Modules
Classifier: Topic :: Internet :: WWW/HTTP :: Dynamic Content
Classifier: Topic :: Software Development :: Libraries :: Python Modules
